{
	"Question": [{
			"id": 1,
			"name": "1 volt is",
			"response": "1 volt equals to 1 J/C"
		},
		{
			"id": 2,
			"name": "2/3 in decimal",
			"response": "0.67"
		},
		{
			"id": 3,
			"name": "What is pi",
			"response": "pi—which is written as the Greek letter for p, or π—is the ratio of the circumference of any circle to the diameter of that circle. Regardless of the circle's size, this ratio will always equal pi. In decimal form, the value of pi is approximately 3.14"
		}
	],
	"Order_no": [{
			"id": 1,
			"number": "12345",
			"response": "Order is being packed and will be shipped out today.",
			"delivery_date": "1st April",
			"phone": "6591282653"
		},
		{
			"id": 2,
			"number": "11111",
			"response": "We are currently processing your order",
			"delivery_date": "10th April",
			"phone": "6591282653"
		},
		{
			"id": 3,
			"number": "22222",
			"response": "Your order is on the way",
			"delivery_date": "2nd April",
			"phone": "6591282653"
		}
	],
	"Phone_no": [{
			"id": 1,
			"Name": "Alvyn Cheang",
			"Agent_ID": "321243",
			"Area" : "Mumbai Metro",
			"phone": "6591282653"
		},
		{
			"id": 2,
			"Name": "Karthik Shetty",
			"Agent_ID": "34312434",
			"Area" : "Bangalore",
			"phone": "919611784404"
		},
		{
			"id": 3,
			"Name": "Jitender",
			"Agent_ID": "42344332",
			"Area" : "Delhi",
			"phone": "919815049533"
		},
		{
			"id": 4,
			"Name": "Parag",
			"Agent_ID": "349980",
			"Area" : "Delhi",
			"phone": "919038008749"
		},
		{
			"id": 5,
			"Name": "Vishal",
			"Agent_ID": "3494243",
			"Area" : "Delhi",
			"phone": "919819571272"
		}
	],
	"Loyalty_no": {
		"Result": {
			"id": "211",
			"points": "1000",
			"name": "Alvyn"
		},
		"id": "222",
		"points": "2000",
		"name": "Aaron"
	},
	"Jumper_order": {
		"Result": [{
				"number": "11111",
				"response": "We are currently processing your order",
				"delivery_date": "10th April",
				"phone": "6591282653"
			},
			{
				"number": "22222",
				"response": "Your order is on the way",
				"delivery_date": "2nd April",
				"phone": "6591282653"
			}
		]
	}

}
